mapproxy/__init__.py
mapproxy/exception.py
mapproxy/featureinfo.py
mapproxy/layer.py
mapproxy/multiapp.py
mapproxy/proj.py
mapproxy/response.py
mapproxy/srs.py
mapproxy/template.py
mapproxy/tilefilter.py
mapproxy/version.py
mapproxy/wsgiapp.py
mapproxy/cache/__init__.py
mapproxy/cache/azureblob.py
mapproxy/cache/base.py
mapproxy/cache/compact.py
mapproxy/cache/couchdb.py
mapproxy/cache/dummy.py
mapproxy/cache/file.py
mapproxy/cache/geopackage.py
mapproxy/cache/legend.py
mapproxy/cache/mbtiles.py
mapproxy/cache/meta.py
mapproxy/cache/path.py
mapproxy/cache/redis.py
mapproxy/cache/renderd.py
mapproxy/cache/s3.py
mapproxy/cache/tile.py
mapproxy/client/__init__.py
mapproxy/client/arcgis.py
mapproxy/client/cgi.py
mapproxy/client/http.py
mapproxy/client/log.py
mapproxy/client/tile.py
mapproxy/client/wms.py
mapproxy/compat/__init__.py
mapproxy/compat/image.py
mapproxy/config/__init__.py
mapproxy/config/config-schema.json
mapproxy/config/config.py
mapproxy/config/coverage.py
mapproxy/config/defaults.py
mapproxy/config/loader.py
mapproxy/config/spec.py
mapproxy/config/validator.py
mapproxy/config_template/__init__.py
mapproxy/config_template/base_config/config.wsgi
mapproxy/config_template/base_config/full_example.yaml
mapproxy/config_template/base_config/full_seed_example.yaml
mapproxy/config_template/base_config/log.ini
mapproxy/config_template/base_config/mapproxy.yaml
mapproxy/config_template/base_config/seed.yaml
mapproxy/grid/__init__.py
mapproxy/grid/meta_grid.py
mapproxy/grid/resolutions.py
mapproxy/grid/tile_grid.py
mapproxy/image/__init__.py
mapproxy/image/mask.py
mapproxy/image/merge.py
mapproxy/image/message.py
mapproxy/image/opts.py
mapproxy/image/tile.py
mapproxy/image/transform.py
mapproxy/image/fonts/DejaVuSans.ttf
mapproxy/image/fonts/DejaVuSansMono.ttf
mapproxy/image/fonts/LICENSE
mapproxy/image/fonts/__init__.py
mapproxy/request/__init__.py
mapproxy/request/arcgis.py
mapproxy/request/base.py
mapproxy/request/tile.py
mapproxy/request/wmts.py
mapproxy-6.0.0.dist-info/licenses/AUTHORS.txt
mapproxy-6.0.0.dist-info/licenses/COPYING.txt
mapproxy-6.0.0.dist-info/licenses/LICENSE.txt
mapproxy-6.0.0.dist-info/METADATA
mapproxy-6.0.0.dist-info/WHEEL
mapproxy-6.0.0.dist-info/entry_points.txt
mapproxy-6.0.0.dist-info/top_level.txt
mapproxy-6.0.0.dist-info/RECORD
