Metadata-Version: 2.4
Name: MapProxy
Version: 6.0.0
Summary: An accelerating proxy for tile and web map services
Home-page: https://mapproxy.org
Author: Oliver Tonnhofer
Author-email: olt@omniscale.de
Maintainer: terrestris GmbH & Co. KG
Maintainer-email: info@terrestris.de
License: Apache Software License 2.0
Classifier: Development Status :: 5 - Production/Stable
Classifier: License :: OSI Approved :: Apache Software License
Classifier: Operating System :: OS Independent
Classifier: Programming Language :: Python :: 3 :: Only
Classifier: Programming Language :: Python :: 3.9
Classifier: Programming Language :: Python :: 3.10
Classifier: Programming Language :: Python :: 3.11
Classifier: Programming Language :: Python :: 3.12
Classifier: Programming Language :: Python :: 3.13
Classifier: Topic :: Internet :: Proxy Servers
Classifier: Topic :: Internet :: WWW/HTTP :: WSGI
Classifier: Topic :: Scientific/Engineering :: GIS
License-File: LICENSE.txt
License-File: COPYING.txt
License-File: AUTHORS.txt
Requires-Dist: PyYAML>=3.0
Requires-Dist: future
Requires-Dist: pyproj>=2
Requires-Dist: jsonschema>=4
Requires-Dist: werkzeug<4
Requires-Dist: Pillow!=8.3.0,!=8.3.1,>=8; python_version == "3.9"
Requires-Dist: Pillow>=9; python_version == "3.10"
Requires-Dist: Pillow>=10; python_version == "3.11"
Requires-Dist: Pillow>=10.1; python_version == "3.12"
Requires-Dist: Pillow>=11; python_version == "3.13"
Requires-Dist: lxml>=6
Requires-Dist: shapely>=2
Requires-Dist: jinja2
Requires-Dist: Babel
Dynamic: author
Dynamic: author-email
Dynamic: classifier
Dynamic: description
Dynamic: description-content-type
Dynamic: home-page
Dynamic: license
Dynamic: license-file
Dynamic: maintainer
Dynamic: maintainer-email
Dynamic: requires-dist
Dynamic: summary
